pyldk/__init__.py
pyldk/hasp_adapter.py
pyldk/pyldk.py
pyldk/version.py
pyldk/lib/Linux/aarch64/libhasp_adapter_aarch64.so
pyldk-1.1.7.dist-info/METADATA
pyldk-1.1.7.dist-info/WHEEL
pyldk-1.1.7.dist-info/top_level.txt
pyldk-1.1.7.dist-info/RECORD
