Metadata-Version: 2.1
Name: pyldk
Version: 1.1.7
Summary: pyldk
Home-page: https://jadehh@live.com
Author: jade
Author-email: jadehh@live.com
License: MIT Licence
Keywords: pip,pyldk,
Platform: any
